MANIFEST.in
README.md
setup.py
data/acc0.dat
data/config.par
data/fixjup_acc0.0.cfg
data/gasdens0.dat
data/gasdens10.dat
data/gasdens100.dat
data/gasdens20.dat
data/gasdens5.dat
data/gasdens50.dat
data/gastracer0_0.dat
data/gastracer0_10.dat
data/gastracer0_100.dat
data/gastracer0_20.dat
data/gastracer0_5.dat
data/gastracer0_50.dat
data/gastracer1_0.dat
data/gastracer1_10.dat
data/gastracer1_100.dat
data/gastracer1_20.dat
data/gastracer1_5.dat
data/gastracer1_50.dat
data/gastracer2_0.dat
data/gastracer2_10.dat
data/gastracer2_100.dat
data/gastracer2_20.dat
data/gastracer2_5.dat
data/gastracer2_50.dat
data/gastracer3_0.dat
data/gastracer3_10.dat
data/gastracer3_100.dat
data/gastracer3_20.dat
data/gastracer3_5.dat
data/gastracer3_50.dat
data/gasvrad0.dat
data/gasvrad10.dat
data/gasvrad100.dat
data/gasvrad20.dat
data/gasvrad5.dat
data/gasvrad50.dat
data/gasvtheta0.dat
data/gasvtheta10.dat
data/gasvtheta100.dat
data/gasvtheta20.dat
data/gasvtheta5.dat
data/gasvtheta50.dat
data/orbit0.dat
data/planet0.dat
data/torque1D0_10.dat
data/torque1D0_100.dat
data/torque1D0_20.dat
data/torque1D0_50.dat
data/tracers.cfg
fyrgo/__init__.py
fyrgo/geometry.py
fyrgo/load.py
fyrgo/phys.py
fyrgo/postprocess.py
fyrgo.egg-info/PKG-INFO
fyrgo.egg-info/SOURCES.txt
fyrgo.egg-info/dependency_links.txt
fyrgo.egg-info/requires.txt
fyrgo.egg-info/top_level.txt
fyrgo/utils/__init__.py
fyrgo/utils/default_planet_format.in
fyrgo/utils/parse.py
fyrgo/utils/scan.py
tests/test_format_parsing.py
tests/test_loading.py
tests/test_planet_auto_load.py
tests/test_postprocessing.py
tests/test_xml_parsing.py